Metadata-Version: 1.1
Name: slacklogging
Version: 0.0.2
Summary: Slack logging integration.
Home-page: https://github.com/narusemotoki/slacklogging
Author: Motoki Naruse
Author-email: motoki@naru.se
License: MIT License
Keywords: logging,slack
Platform: UNKNOWN
Classifier: Programming Language :: Python
Classifier: Programming Language :: Python :: 3
Classifier: Programming Language :: Python :: 3.6
Classifier: Programming Language :: Python :: 3 :: Only
Classifier: License :: OSI Approved :: MIT License
